{
    "id": "mNCoovdhIGo",
    "title": "Could it be a rare pokemon cought in the wild ?",
    "duration": {
        "secondsText": "62"
    },
    "viewCount": {
        "text": "54"
    },
    "thumbnails": [
        {
            "url": "https://i.ytimg.com/vi_webp/mNCoovdhIGo/default.webp?v=5c9c8bd4",
            "width": 120,
            "height": 90
        },
        {
            "url": "https://i.ytimg.com/vi_webp/mNCoovdhIGo/mqdefault.webp?v=5c9c8bd4",
            "width": 320,
            "height": 180
        },
        {
            "url": "https://i.ytimg.com/vi_webp/mNCoovdhIGo/hqdefault.webp?v=5c9c8bd4",
            "width": 480,
            "height": 360
        },
        {
            "url": "https://i.ytimg.com/vi_webp/mNCoovdhIGo/sddefault.webp?v=5c9c8bd4",
            "width": 640,
            "height": 480
        },
        {
            "url": "https://i.ytimg.com/vi/mNCoovdhIGo/hq720.jpg?sqp=-oaymwEcCK4FEIIDSEbyq4qpAw4IARUAAIhCGAFwAcABBg==&rs=AOn4CLCbUnk8Uq0uBrwTC4jfE8YkUiaxfg",
            "width": 686,
            "height": 386
        }
    ],
    "description": "if you enjoyed this video, do not forget to subscribe and smash that like button and share this video for more amassing videos.\n\n\n\n\n\n\n#DURecorder   #Arvindkumar    #WassupFolks    #JonnoPlays    #pokemon   #Pok\u00e9monGO   #LiftingandZombies    \nThis is my video recorded with DU Recorder. It's easy to record your screen and livestream. Download link: \nAndroid: https://goo.gl/s9D6Mf\niOS: https://goo.gl/nXnxyN",
    "channel": {
        "name": "GODOFTHUNDER",
        "id": "UCEN4FPllLLKz35QS1T7SgaA",
        "link": "https://www.youtube.com/channel/UCEN4FPllLLKz35QS1T7SgaA"
    },
    "allowRatings": true,
    "averageRating": null,
    "keywords": [
        "DU Recorder",
        "#WassupFolks",
        "#JonnoPlays",
        "#pokemon",
        "#Pok\u00e9monGO",
        "#LiftingandZombies",
        "#Arvindkumar"
    ],
    "isLiveContent": false,
    "publishDate": "2019-03-28",
    "uploadDate": "2019-03-28",
    "isFamilySafe": true,
    "category": "Gaming",
    "isLiveNow": false,
    "link": "https://www.youtube.com/watch?v=mNCoovdhIGo",
    "Time search": "2023-02-17 19:43:48.569301"
}