{
    "id": "vxWItaxZs_I",
    "title": "[Root Hack] Pokemon Go 0.123.1 | Spoofing In Rooted Android Devices | through all the Security patch",
    "duration": {
        "secondsText": "859"
    },
    "viewCount": {
        "text": "4999"
    },
    "thumbnails": [
        {
            "url": "https://i.ytimg.com/vi_webp/vxWItaxZs_I/default.webp",
            "width": 120,
            "height": 90
        },
        {
            "url": "https://i.ytimg.com/vi_webp/vxWItaxZs_I/mqdefault.webp",
            "width": 320,
            "height": 180
        },
        {
            "url": "https://i.ytimg.com/vi_webp/vxWItaxZs_I/hqdefault.webp",
            "width": 480,
            "height": 360
        }
    ],
    "description": "#PokemonGo #PokemonGoSpoofing #September2018Security  \n\nSorry for the low quality sound my mic needs to be fixed I didn't realise until I uploaded this video but if you still enjoyed this video make sure to subscribe and smash that like button and share this video for more amazing videos \n\n\n\n\n\n\n\nHi I am GODOFTHUNDER . Welcome to my youtube  channel GODOFTHUNDER. About this Video:- This video is about how to root your device and play pokemon go on the rooted android device. I have shown each and every necessary step which we need to root Android devices and how to hide magisk manager from pokemon go in order to play without any error. So don't skip the video watch it till the end. Thanks for watching guys, if you have any question or suggestion then please comment. If this video is helpful then like share and subscribe. .................................................................................................................. About This Channel:- 1. Tips and tricks for Android spoofing. 2. Learn how to spoof in android. 3. Solutions to all android spoofing problem. 4. Ask any questions related to spoofing. 5. Plss like share and comment .................................................................................................................. Important Link;- 1. Pokemon Go App:- https://play.google.com/store/apps/de... 2. GPS JoyStick Fake GPS Location:- https://play.google.com/store/apps/de... 3. Download Recovery For Your Device:- https://twrp.me/Devices/ 4. Magisk Manager Zip File:- https://forum.xda-developers.com/apps... 5. ADB Setup Link- 01:56 https://drive.google.com/file/d/0B0MK... .................................................................................................................. Some Other Useful Videos Links:- * How To Downgrade Google Play Services And Auto Update Fix Working Hack! Android 8.0 $ 8.1 channel gameXgame. About this Video:- This video is about how to root your device and play pokemon go on the rooted android device. I have shown each and every necessary step which we need to root Android devices and how to hide magisk manager from pokemon go in order to play without any error. So don't skip the video watch it till the end. Thanks for watching guys, if you have any question or suggestion then please comment. If this video is helpful then like share and subscribe. .................................................................................................................. About This Channel:- 1. Tips and tricks for Android spoofing. 2. Learn how to spoof in android. 3. Solutions to all android spoofing problem. 4. Ask any questions related to spoofing. 5. Plss like share and comment .................................................................................................................. Important Link;- 1. Pokemon Go App:- https://play.google.com/store/apps/de... 2. GPS JoyStick Fake GPS Location:- https://play.google.com/store/apps/de... 3. Download Recovery For Your Device:- https://twrp.me/Devices/ 4. Magisk Manager Zip File:- https://forum.xda-developers.com/apps... 5. ADB Setup Link- 01:56 https://drive.google.com/file/d/0B0MK... .................................................................................................................. Some Other Useful Videos Links:- * How To Downgrade Google Play Services And Auto Update Fix Working Hack! Android 8.0 $ 8.1 \n\n\n\n\n\n\n\n\n\n\n\nTags :\n\n#DURecorder   \n#Unlimited pokemon hack\n#Pokemon go mewtwo HACK\n#Unlimited item HACK for pokemon go\n#Pokemon go lagandry hack\n#Pokemon go best hacks\n#Pok\u00e9mon go hack 0.139.1,\n#Pok\u00e9mon go hack android 2019,\n#New hack for Pok\u00e9mon go,\n#Spoofing Pok\u00e9mon go,\n#Pok\u00e9mon go update,\n#Pok\u00e9mon go new hack,\n#Pok\u00e9mon go hack play service 12.6.85,\n#How to downgrade Pok\u00e9mon go,\n\n#pokemon go hack android download\n#pokemon go hack android no root\n#pokemon go hack apk\n#pokemon go hack apk ios\n#pokemon go hack app tutu\n#pokemon go hack apps\n#pokemon go hack april 2017\n#pokemon go hack ban\n#pokemon go hack best\n#pokemon go hack best locations\n#pokemon go hack bgr\n#pokemon go hack bluestacks\n#pokemon go hack bluestacks joystick\n#pokemon go hack bot\n#pokemon go hack bot download\n#pokemon go hack bunny\n#pokemon go hack buttons\n#pokemon go hack candy\n#pokemon go hack change home location\n#pokemon go hack chinese\n#pokemon go hack codes\n#pokemon go hack coins\n#pokemon go hack computer\n#pokemon go hack coordinates\n#pokemon go hack crashing\n#pokemon go hack cydia\n#pokemon go hack cydia impactor\n#pokemon go hack devs lab\n#pokemon go hack discord\n#pokemon go hack ditto\n#pokemon go hack download\n#pokemon go hack download android\n#pokemon go hack download android no root\n#pokemon go hack download ios\n#pokemon go hack download iphone\n#pokemon go hack download pc\n#pokemon go hack download tutuapp\n#pokemon go hack easy\n#pokemon go hack easy download",
    "channel": {
        "name": "GODOFTHUNDER",
        "id": "UCEN4FPllLLKz35QS1T7SgaA",
        "link": "https://www.youtube.com/channel/UCEN4FPllLLKz35QS1T7SgaA"
    },
    "allowRatings": true,
    "averageRating": null,
    "keywords": [
        "DU Recorder"
    ],
    "isLiveContent": false,
    "publishDate": "2019-04-05",
    "uploadDate": "2019-04-05",
    "isFamilySafe": true,
    "category": "Gaming",
    "isLiveNow": false,
    "link": "https://www.youtube.com/watch?v=vxWItaxZs_I",
    "Time search": "2023-02-17 19:43:48.569301"
}